graphql_booster/__init__.py
graphql_booster/install.py
graphql_booster/gateway/index.js
graphql_booster/gateway/package-lock.json
graphql_booster/gateway/package.json
graphql_booster/services/__init__.py
graphql_booster/types/__init__.py
graphql_booster/types/directive.py
graphql_booster/types/entity.py
graphql_booster/types/gateway.py
graphql_booster/types/objects.py
graphql_booster/types/scalars.py
graphql_booster/types/service.py
graphql_booster/types/service_manager.py
graphql_booster-0.0.1a5.dist-info/LICENSE
graphql_booster-0.0.1a5.dist-info/METADATA
graphql_booster-0.0.1a5.dist-info/WHEEL
graphql_booster-0.0.1a5.dist-info/top_level.txt
graphql_booster-0.0.1a5.dist-info/RECORD
